log_psplines/__init__.py
log_psplines/_version.py
log_psplines/datatypes.py
log_psplines/mcmc.py
log_psplines/psd_diagnostics.py
log_psplines/types.py
log_psplines/arviz_utils/__init__.py
log_psplines/arviz_utils/compare_results.py
log_psplines/arviz_utils/from_arviz.py
log_psplines/arviz_utils/to_arviz.py
log_psplines/benchmark/__init__.py
log_psplines/benchmark/cli.py
log_psplines/benchmark/plotting.py
log_psplines/benchmark/runtime_benchmark.py
log_psplines/example_datasets/__init__.py
log_psplines/example_datasets/ar_data.py
log_psplines/example_datasets/lvk_data.py
log_psplines/plotting/__init__.py
log_psplines/plotting/diagnostics.py
log_psplines/plotting/pdgrm.py
log_psplines/plotting/plot_ess_evolution.py
log_psplines/plotting/utils.py
log_psplines/psplines/__init__.py
log_psplines/psplines/initialisation.py
log_psplines/psplines/plot_basis.py
log_psplines/psplines/psplines.py
log_psplines/psplines/knots_locator/__init__.py
log_psplines/psplines/knots_locator/knot_locator.py
log_psplines/psplines/knots_locator/lvk_knot_allocator.py
log_psplines/samplers/__init__.py
log_psplines/samplers/base_sampler.py
log_psplines/samplers/metropolis_hastings.py
log_psplines/samplers/nuts.py
logpsplinepsd-0.0.13.dist-info/licenses/LICENSE
logpsplinepsd-0.0.13.dist-info/METADATA
logpsplinepsd-0.0.13.dist-info/WHEEL
logpsplinepsd-0.0.13.dist-info/entry_points.txt
logpsplinepsd-0.0.13.dist-info/top_level.txt
logpsplinepsd-0.0.13.dist-info/RECORD
