Metadata-Version: 2.4
Name: LogPSplinePSD
Version: 0.0.13
Summary: LogPsplines in JAX
Author-email: Avi Vajpeyi <avi.vajpeyi@gmail.com>
Project-URL: Homepage, https://starccato.github.io/log_psplines/
Project-URL: Bug Reports, https://giuthub.com/starccato/log_psplines/issues
Project-URL: Source, https://github.com/starccato/log_psplines/
Classifier: Development Status :: 3 - Alpha
Classifier: Intended Audience :: Science/Research
Classifier: License :: OSI Approved :: MIT License
Classifier: Operating System :: OS Independent
Classifier: Programming Language :: Python :: 3.8
Requires-Python: >=3.9
License-File: LICENSE
Requires-Dist: scikit-fda
Requires-Dist: jax<=0.7.0
Requires-Dist: optax
Requires-Dist: numpy
Requires-Dist: matplotlib
Requires-Dist: tqdm
Requires-Dist: numpyro
Requires-Dist: arviz
Requires-Dist: click
Requires-Dist: ipywidgets
Requires-Dist: plotly
Provides-Extra: gw
Requires-Dist: gwpy>=1.3.0; extra == "gw"
Requires-Dist: gwosc; extra == "gw"
Provides-Extra: dev
Requires-Dist: pytest; extra == "dev"
Requires-Dist: pytest-cov; extra == "dev"
Requires-Dist: pytest-durations; extra == "dev"
Requires-Dist: flake8>=5.0.4; extra == "dev"
Requires-Dist: black>=22.12.0; extra == "dev"
Requires-Dist: black[jupyter]>=22.12.0; extra == "dev"
Requires-Dist: isort; extra == "dev"
Requires-Dist: mypy; extra == "dev"
Requires-Dist: jupyter-book; extra == "dev"
Requires-Dist: pre-commit; extra == "dev"
Requires-Dist: gwpy>=1.3.0; extra == "dev"
Dynamic: license-file
